osgeo_easy/__init__.py
osgeo_easy/crs.py
osgeo_easy/multitype.py
osgeo_easy/raster.py
osgeo_easy/vector.py
OSGeo_Easy-0.0.1.dev16.dist-info/LICENSE
OSGeo_Easy-0.0.1.dev16.dist-info/METADATA
OSGeo_Easy-0.0.1.dev16.dist-info/WHEEL
OSGeo_Easy-0.0.1.dev16.dist-info/top_level.txt
OSGeo_Easy-0.0.1.dev16.dist-info/RECORD
