Metadata-Version: 2.1
Name: OSGeo-Easy
Version: 0.0.1.dev16
Summary: UNKNOWN
Home-page: https://github.com/adlzanchetta/osgeo_easy
Author: Andre Della Libera Zanchetta
Author-email: adlzanchetta@gmail.com
License: GNU General Public License v2.0
Platform: UNKNOWN
Classifier: Programming Language :: Python :: 3
Classifier: Operating System :: OS Independent
Requires-Python: >=3, <4
Requires-Dist: numpy
Requires-Dist: GDAL
Requires-Dist: pillow
